exonware/xaction/__init__.py
exonware/xaction/version.py
exonware/xwaction/__init__.py
exonware/xwaction/base.py
exonware/xwaction/config.py
exonware/xwaction/context.py
exonware/xwaction/contracts.py
exonware/xwaction/defs.py
exonware/xwaction/errors.py
exonware/xwaction/registry.py
exonware/xwaction/version.py
exonware/xwaction/core/__init__.py
exonware/xwaction/core/profiles.py
exonware_xwaction-0.1.0.1.dist-info/METADATA
exonware_xwaction-0.1.0.1.dist-info/WHEEL
exonware_xwaction-0.1.0.1.dist-info/licenses/LICENSE
exonware_xwaction-0.1.0.1.dist-info/RECORD
